telefier/__init__.py
telefier/app.py
telefier-0.0.3.dist-info/LICENSE.md
telefier-0.0.3.dist-info/METADATA
telefier-0.0.3.dist-info/WHEEL
telefier-0.0.3.dist-info/top_level.txt
telefier-0.0.3.dist-info/RECORD
