Metadata-Version: 2.1
Name: telefier
Version: 0.0.3
Summary: Telegram notifier utility
Home-page: https://github.com/ablil/telefier
Author: ablil
Author-email: ablil@protonmail.com
Project-URL: Bug Tracker, https://github.com/ablil/telefier/issues
Classifier: Programming Language :: Python :: 3
Classifier: License :: OSI Approved :: MIT License
Classifier: Operating System :: OS Independent
Requires-Python: >=3.2
License-File: LICENSE.md
Requires-Dist: telethon
